bastila_search/__init__.py
bastila_search/bastila_search.py
bastila_search/setup_config.py
bastila_search-0.4.3.dist-info/LICENSE
bastila_search-0.4.3.dist-info/METADATA
bastila_search-0.4.3.dist-info/WHEEL
bastila_search-0.4.3.dist-info/entry_points.txt
bastila_search-0.4.3.dist-info/top_level.txt
bastila_search-0.4.3.dist-info/RECORD
